granulemeta/__init__.py
granulemeta/granulemeta.py
granulemeta/config/CONFIG_FILE_DESIGN_DOC.md
granulemeta/config/GranuleMetaFormatTypes.cfg
granulemeta/config/configuration_parser.py
granulemeta/config/daymet.cfg
granulemeta/config/default.cfg
granulemeta/config/kitchen_sink.cfg
granulemeta/scripts/add_ext.py
granulemeta/scripts/gmout.py
granulemeta/scripts/parse_archive.py
granulemeta/scripts/parse_arguments.py
granulemeta/scripts/parse_audio.py
granulemeta/scripts/parse_envi.py
granulemeta/scripts/parse_mdim.py
granulemeta/scripts/parse_raster.py
granulemeta/scripts/parse_table.py
granulemeta/scripts/parse_vector.py
granulemeta/scripts/process_daymet.py
granulemeta/scripts/utilities.py
granulemeta/scripts/validate_cloud_optimized_geotiff.py
granulemeta-3.3.2.dist-info/METADATA
granulemeta-3.3.2.dist-info/WHEEL
granulemeta-3.3.2.dist-info/entry_points.txt
granulemeta-3.3.2.dist-info/license_files/LICENSE
granulemeta-3.3.2.dist-info/RECORD
