Metadata-Version: 2.1
Name: granulemeta
Version: 3.3.2
Summary: A package designed to generate low-level metadata in a specified/supported format (i.e. gmout) for a file or set of files.
Project-URL: Homepage, https://github.com/ornldaac/granulemeta
Author-email: "Kent B. Campbell" <campbellkb@ornl.gov>
License: Open Source License
Classifier: Operating System :: POSIX :: Linux
Classifier: Operating System :: Unix
Classifier: Programming Language :: Python :: 3
Requires-Python: >=3.6
Requires-Dist: gdal>=3.0.4
Requires-Dist: netcdf4>=1.5.3
Requires-Dist: numpy>=1.18.1
Requires-Dist: pandas>=1.0.0
Requires-Dist: tinytag>=1.4.0
